cherrry.py
cherrry-0.0.2.dist-info/LICENSE.md
cherrry-0.0.2.dist-info/METADATA
cherrry-0.0.2.dist-info/WHEEL
cherrry-0.0.2.dist-info/top_level.txt
cherrry-0.0.2.dist-info/RECORD
