Metadata-Version: 2.1
Name: cherrry
Version: 0.0.2
Summary: Cherrry Semantic Search API SDK
Home-page: https://github.com/cherrry-ai/cherrry-py
Author: Lukas Kelsey-Friedemann
Classifier: Programming Language :: Python :: 3
Classifier: License :: OSI Approved :: Apache Software License
Classifier: Operating System :: OS Independent
Requires-Python: >=3.6
License-File: LICENSE.md
Requires-Dist: requests
